MANIFEST.in
README.rst
setup.py
docs/Makefile
docs/changes.rst
docs/conf.py
docs/forms.rst
docs/index.rst
docs/mobile-visibility.rst
docs/modal.rst
docs/top-nav-bar.rst
pinax_theme_foundation/__init__.py
pinax_theme_foundation/urls.py
pinax_theme_foundation.egg-info/PKG-INFO
pinax_theme_foundation.egg-info/SOURCES.txt
pinax_theme_foundation.egg-info/dependency_links.txt
pinax_theme_foundation.egg-info/not-zip-safe
pinax_theme_foundation.egg-info/top_level.txt
pinax_theme_foundation/static/foundation/css/app.css
pinax_theme_foundation/static/foundation/css/fc-webicons.css
pinax_theme_foundation/static/foundation/css/foundation.css
pinax_theme_foundation/static/foundation/css/ie.css
pinax_theme_foundation/static/foundation/css/offcanvas.css
pinax_theme_foundation/static/foundation/css/responsive-tables.css
pinax_theme_foundation/static/foundation/css/fonts/accessibility.css
pinax_theme_foundation/static/foundation/css/fonts/accessibility_ie7.css
pinax_theme_foundation/static/foundation/css/fonts/general.css
pinax_theme_foundation/static/foundation/css/fonts/general_enclosed.css
pinax_theme_foundation/static/foundation/css/fonts/general_enclosed_ie7.css
pinax_theme_foundation/static/foundation/css/fonts/general_ie7.css
pinax_theme_foundation/static/foundation/css/fonts/social.css
pinax_theme_foundation/static/foundation/css/fonts/social_ie7.css
pinax_theme_foundation/static/foundation/images/foundation/spinner.gif
pinax_theme_foundation/static/foundation/images/foundation/fairhead-icons/fc-webicon-behance-m.png
pinax_theme_foundation/static/foundation/images/foundation/fairhead-icons/fc-webicon-behance-s.png
pinax_theme_foundation/static/foundation/images/foundation/fairhead-icons/fc-webicon-behance.png
pinax_theme_foundation/static/foundation/images/foundation/fairhead-icons/fc-webicon-behance.svg
pinax_theme_foundation/static/foundation/images/foundation/fairhead-icons/fc-webicon-creativecloud-m.png
pinax_theme_foundation/static/foundation/images/foundation/fairhead-icons/fc-webicon-creativecloud-s.png
pinax_theme_foundation/static/foundation/images/foundation/fairhead-icons/fc-webicon-creativecloud.png
