Metadata-Version: 1.0
Name: pinax-theme-foundation
Version: 0.2.3
Summary: Pinax theme based on Zurb's Foundation
Home-page: http://github.com/chrisdev/pinax-theme-foundation
Author: Chris Clarke
Author-email: cclarke@chrisdev.com
License: MIT
Platform: UNKNOWN
Classifier: Development Status :: 3 - Alpha
Classifier: Environment :: Web Environment
Classifier: Intended Audience :: Developers
Classifier: License :: OSI Approved :: BSD License
Classifier: Operating System :: OS Independent
Classifier: Programming Language :: Python
Classifier: Framework :: Django
